mathy_pydoc/__init__.py
mathy_pydoc/about.py
mathy_pydoc/cli.py
mathy_pydoc/document.py
mathy_pydoc/imp.py
mathy_pydoc/loader.py
mathy_pydoc/preprocessor.py
mathy_pydoc-0.7.30.dist-info/LICENSE.txt
mathy_pydoc-0.7.30.dist-info/METADATA
mathy_pydoc-0.7.30.dist-info/WHEEL
mathy_pydoc-0.7.30.dist-info/entry_points.txt
mathy_pydoc-0.7.30.dist-info/top_level.txt
mathy_pydoc-0.7.30.dist-info/RECORD
