Metadata-Version: 2.1
Name: mathy-pydoc
Version: 0.7.30
Summary: Minimal python API documentation generation for https://mathy.ai
Home-page: https://github.com/mathy/mathy_pydoc
Author: Justin DuJardin
Author-email: justin@dujardinconsulting.com
License: MIT
Keywords: markdown pydoc generator docs documentation
Classifier: Development Status :: 3 - Alpha
Classifier: Intended Audience :: Developers
Classifier: Intended Audience :: End Users/Desktop
Classifier: Topic :: Software Development :: Code Generators
Classifier: Topic :: Utilities
Classifier: License :: OSI Approved :: MIT License
Classifier: Programming Language :: Python :: 3
Classifier: Programming Language :: Python :: 3.6
Classifier: Programming Language :: Python :: 3.7
Classifier: Programming Language :: Python :: 3.8
License-File: LICENSE.txt
Requires-Dist: typer <0.10.0,>=0.3.0
Requires-Dist: Markdown >=2.6.11
Requires-Dist: dataclasses <1.0,>=0.6 ; python_version < "3.7"
Requires-Dist: typing-extensions <4.0.0.0,>=3.7.4.1 ; python_version < "3.7"
